{
  "parent": "golems:generic_log",
  "hidden": false,
  "blocks": {
	"arms": "#minecraft:logs_that_burn",
	"legs": "#minecraft:logs_that_burn",
	"body": "#thermal:rubberwood_logs"
  },
  "model": "thermal:rubberwood_log",
  "brain": {
	"behaviors": [
	  {
		"type": "golems:item_update_golem",
		"item": "#minecraft:axes",
		"display_name": "golem.description.axe",
		"sound": "minecraft:item.axe.strip",
		"particle": {
		  "type": "minecraft:item",
		  "value": {
			"id": "minecraft:acacia_log",
			"Count": 1
		  }
		},
		"apply": {
		  "golem": "thermal:stripped_rubberwood_log"
		}
	  }
	]
  }
}
